{
    "name": "Thelia\\Form\\OrderDelivery",
    "line": 36,
    "short_desc": "Class OrderDelivery",
    "long_desc": "",
    "hint": null,
    "tags": {
        "package": [
            [
                "Thelia\\Form"
            ]
        ],
        "author": [
            [
                "Etienne",
                "Roudeix",
                "<eroudeix@openstudio.fr>"
            ]
        ]
    },
    "namespace": "Thelia\\Form",
    "file": "\/home\/manu\/dev\/www\/thelia\/core\/lib\/Thelia\/Form\/OrderDelivery.php",
    "hash": "f48a7a92e53110ec9220980fc10de37585f264e6",
    "parent": "Thelia\\Form\\BaseForm",
    "modifiers": 0,
    "is_trait": false,
    "is_interface": false,
    "aliases": {
        "Constraints": "Symfony\\Component\\Validator\\Constraints",
        "ExecutionContextInterface": "Symfony\\Component\\Validator\\ExecutionContextInterface",
        "AddressQuery": "Thelia\\Model\\AddressQuery",
        "ModuleQuery": "Thelia\\Model\\ModuleQuery",
        "BaseModule": "Thelia\\Module\\BaseModule"
    },
    "errors": [

    ],
    "interfaces": [

    ],
    "properties": [

    ],
    "methods": {
        "verifyDeliveryAddress": {
            "name": "verifyDeliveryAddress",
            "line": 65,
            "short_desc": "",
            "long_desc": "",
            "hint": null,
            "hint_desc": null,
            "tags": [

            ],
            "modifiers": "1",
            "is_by_ref": "",
            "exceptions": [

            ],
            "errors": [

            ],
            "parameters": {
                "value": {
                    "name": "value",
                    "line": 65,
                    "short_desc": null,
                    "long_desc": null,
                    "hint": null,
                    "tags": [

                    ],
                    "modifiers": "",
                    "default": null,
                    "is_by_ref": false
                },
                "context": {
                    "name": "context",
                    "line": 65,
                    "short_desc": null,
                    "long_desc": null,
                    "hint": [
                        [
                            "Symfony\\Component\\Validator\\ExecutionContextInterface",
                            false
                        ]
                    ],
                    "tags": [

                    ],
                    "modifiers": "ExecutionContextInterface",
                    "default": null,
                    "is_by_ref": false
                }
            }
        },
        "verifyDeliveryModule": {
            "name": "verifyDeliveryModule",
            "line": 75,
            "short_desc": "",
            "long_desc": "",
            "hint": null,
            "hint_desc": null,
            "tags": [

            ],
            "modifiers": "1",
            "is_by_ref": "",
            "exceptions": [

            ],
            "errors": [

            ],
            "parameters": {
                "value": {
                    "name": "value",
                    "line": 75,
                    "short_desc": null,
                    "long_desc": null,
                    "hint": null,
                    "tags": [

                    ],
                    "modifiers": "",
                    "default": null,
                    "is_by_ref": false
                },
                "context": {
                    "name": "context",
                    "line": 75,
                    "short_desc": null,
                    "long_desc": null,
                    "hint": [
                        [
                            "Symfony\\Component\\Validator\\ExecutionContextInterface",
                            false
                        ]
                    ],
                    "tags": [

                    ],
                    "modifiers": "ExecutionContextInterface",
                    "default": null,
                    "is_by_ref": false
                }
            }
        },
        "getName": {
            "name": "getName",
            "line": 95,
            "short_desc": "",
            "long_desc": "",
            "hint": [
                [
                    "string",
                    false
                ]
            ],
            "hint_desc": "the name of you form. This name must be unique",
            "tags": [

            ],
            "modifiers": "1",
            "is_by_ref": "",
            "exceptions": [

            ],
            "errors": [

            ],
            "parameters": [

            ]
        }
    },
    "constants": [

    ]
}