{
    "name": "Thelia\\Controller\\Admin\\CacheController",
    "line": 27,
    "short_desc": "Class CacheController",
    "long_desc": "",
    "hint": null,
    "tags": {
        "package": [
            [
                "Thelia\\Controller\\Admin"
            ]
        ],
        "author": [
            [
                "Manuel",
                "Raynaud",
                "<mraynaud@openstudio.fr>"
            ]
        ]
    },
    "namespace": "Thelia\\Controller\\Admin",
    "file": "\/home\/manu\/dev\/www\/thelia\/core\/lib\/Thelia\/Controller\/Admin\/CacheController.php",
    "hash": "bd23baa4c8a51752dbc0935d01bf08ce72886038",
    "parent": "Thelia\\Controller\\Admin\\BaseAdminController",
    "modifiers": 0,
    "is_trait": false,
    "is_interface": false,
    "aliases": {
        "CacheEvent": "Thelia\\Core\\Event\\Cache\\CacheEvent",
        "TheliaEvents": "Thelia\\Core\\Event\\TheliaEvents",
        "AccessManager": "Thelia\\Core\\Security\\AccessManager",
        "AdminResources": "Thelia\\Core\\Security\\Resource\\AdminResources",
        "CacheFlushForm": "Thelia\\Form\\Cache\\CacheFlushForm",
        "FormValidationException": "Thelia\\Form\\Exception\\FormValidationException"
    },
    "errors": [

    ],
    "interfaces": [

    ],
    "properties": [

    ],
    "methods": {
        "defaultAction": {
            "name": "defaultAction",
            "line": 30,
            "short_desc": "",
            "long_desc": "",
            "hint": null,
            "hint_desc": null,
            "tags": [

            ],
            "modifiers": "1",
            "is_by_ref": "",
            "exceptions": [

            ],
            "errors": [

            ],
            "parameters": [

            ]
        },
        "flushAction": {
            "name": "flushAction",
            "line": 39,
            "short_desc": "",
            "long_desc": "",
            "hint": null,
            "hint_desc": null,
            "tags": [

            ],
            "modifiers": "1",
            "is_by_ref": "",
            "exceptions": [

            ],
            "errors": [

            ],
            "parameters": [

            ]
        }
    },
    "constants": [

    ]
}