{
    "name": "Thelia\\Model\\Content",
    "line": 14,
    "short_desc": "",
    "long_desc": "",
    "hint": null,
    "tags": [

    ],
    "namespace": "Thelia\\Model",
    "file": "\/home\/manu\/dev\/www\/thelia\/core\/lib\/Thelia\/Model\/Content.php",
    "hash": "ff7bcc8da5a771f97305b00740e16bdcd9caef7f",
    "parent": "Thelia\\Model\\Base\\Content",
    "modifiers": 0,
    "is_trait": false,
    "is_interface": false,
    "aliases": {
        "Propel": "Propel\\Runtime\\Propel",
        "ContentEvent": "Thelia\\Core\\Event\\Content\\ContentEvent",
        "TheliaEvents": "Thelia\\Core\\Event\\TheliaEvents",
        "BaseContent": "Thelia\\Model\\Base\\Content",
        "ContentFolderQuery": "Thelia\\Model\\ContentFolderQuery",
        "ContentTableMap": "Thelia\\Model\\Map\\ContentTableMap",
        "URL": "Thelia\\Tools\\URL",
        "ConnectionInterface": "Propel\\Runtime\\Connection\\ConnectionInterface"
    },
    "errors": [

    ],
    "interfaces": [

    ],
    "properties": [

    ],
    "methods": {
        "getDefaultFolderId": {
            "name": "getDefaultFolderId",
            "line": 38,
            "short_desc": "",
            "long_desc": "",
            "hint": null,
            "hint_desc": null,
            "tags": [

            ],
            "modifiers": "1",
            "is_by_ref": "",
            "exceptions": [

            ],
            "errors": [

            ],
            "parameters": [

            ]
        },
        "setDefaultFolder": {
            "name": "setDefaultFolder",
            "line": 49,
            "short_desc": "",
            "long_desc": "",
            "hint": null,
            "hint_desc": null,
            "tags": [

            ],
            "modifiers": "1",
            "is_by_ref": "",
            "exceptions": [

            ],
            "errors": [

            ],
            "parameters": {
                "folderId": {
                    "name": "folderId",
                    "line": 49,
                    "short_desc": null,
                    "long_desc": null,
                    "hint": null,
                    "tags": [

                    ],
                    "modifiers": "",
                    "default": null,
                    "is_by_ref": false
                }
            }
        },
        "updateDefaultFolder": {
            "name": "updateDefaultFolder",
            "line": 59,
            "short_desc": "",
            "long_desc": "",
            "hint": null,
            "hint_desc": null,
            "tags": [

            ],
            "modifiers": "1",
            "is_by_ref": "",
            "exceptions": [

            ],
            "errors": [

            ],
            "parameters": {
                "defaultFolderId": {
                    "name": "defaultFolderId",
                    "line": 59,
                    "short_desc": null,
                    "long_desc": null,
                    "hint": null,
                    "tags": [

                    ],
                    "modifiers": "",
                    "default": null,
                    "is_by_ref": false
                }
            }
        },
        "create": {
            "name": "create",
            "line": 99,
            "short_desc": "Create a new content.",
            "long_desc": "Here pre and post insert event are fired",
            "hint": null,
            "hint_desc": null,
            "tags": [

            ],
            "modifiers": "1",
            "is_by_ref": "",
            "exceptions": [
                [
                    "\\Exception",
                    ""
                ]
            ],
            "errors": [

            ],
            "parameters": {
                "defaultFolderId": {
                    "name": "defaultFolderId",
                    "line": 99,
                    "short_desc": "",
                    "long_desc": null,
                    "hint": [
                        [
                            "Thelia\\Model\\$defaultFolderId",
                            false
                        ]
                    ],
                    "tags": [

                    ],
                    "modifiers": "",
                    "default": null,
                    "is_by_ref": false
                }
            }
        },
        "preUpdate": {
            "name": "preUpdate",
            "line": 130,
            "short_desc": "Code to be run before updating the object in database",
            "long_desc": "",
            "hint": [
                [
                    "boolean",
                    false
                ]
            ],
            "hint_desc": "",
            "tags": [

            ],
            "modifiers": "1",
            "is_by_ref": "",
            "exceptions": [

            ],
            "errors": [

            ],
            "parameters": {
                "con": {
                    "name": "con",
                    "line": 130,
                    "short_desc": "",
                    "long_desc": null,
                    "hint": [
                        [
                            "Propel\\Runtime\\Connection\\ConnectionInterface",
                            false
                        ]
                    ],
                    "tags": [

                    ],
                    "modifiers": "ConnectionInterface",
                    "default": "null",
                    "is_by_ref": false
                }
            }
        },
        "postUpdate": {
            "name": "postUpdate",
            "line": 137,
            "short_desc": "Code to be run after updating the object in database",
            "long_desc": "",
            "hint": null,
            "hint_desc": null,
            "tags": [

            ],
            "modifiers": "1",
            "is_by_ref": "",
            "exceptions": [

            ],
            "errors": [

            ],
            "parameters": {
                "con": {
                    "name": "con",
                    "line": 137,
                    "short_desc": "",
                    "long_desc": null,
                    "hint": [
                        [
                            "Propel\\Runtime\\Connection\\ConnectionInterface",
                            false
                        ]
                    ],
                    "tags": [

                    ],
                    "modifiers": "ConnectionInterface",
                    "default": "null",
                    "is_by_ref": false
                }
            }
        },
        "preDelete": {
            "name": "preDelete",
            "line": 142,
            "short_desc": "Code to be run before deleting the object in database",
            "long_desc": "",
            "hint": [
                [
                    "boolean",
                    false
                ]
            ],
            "hint_desc": "",
            "tags": [

            ],
            "modifiers": "1",
            "is_by_ref": "",
            "exceptions": [

            ],
            "errors": [

            ],
            "parameters": {
                "con": {
                    "name": "con",
                    "line": 142,
                    "short_desc": "",
                    "long_desc": null,
                    "hint": [
                        [
                            "Propel\\Runtime\\Connection\\ConnectionInterface",
                            false
                        ]
                    ],
                    "tags": [

                    ],
                    "modifiers": "ConnectionInterface",
                    "default": "null",
                    "is_by_ref": false
                }
            }
        },
        "postDelete": {
            "name": "postDelete",
            "line": 149,
            "short_desc": "Code to be run after deleting the object in database",
            "long_desc": "",
            "hint": null,
            "hint_desc": null,
            "tags": [

            ],
            "modifiers": "1",
            "is_by_ref": "",
            "exceptions": [

            ],
            "errors": [

            ],
            "parameters": {
                "con": {
                    "name": "con",
                    "line": 149,
                    "short_desc": "",
                    "long_desc": null,
                    "hint": [
                        [
                            "Propel\\Runtime\\Connection\\ConnectionInterface",
                            false
                        ]
                    ],
                    "tags": [

                    ],
                    "modifiers": "ConnectionInterface",
                    "default": "null",
                    "is_by_ref": false
                }
            }
        }
    },
    "constants": [

    ]
}