{
    "name": "Thelia\\Condition\\Implementation\\MatchForXArticlesManager",
    "line": 43,
    "short_desc": "Created by JetBrains PhpStorm.",
    "long_desc": "Date: 8\/19\/13\nTime: 3:24 PM\n\nCheck a Checkout against its Product number",
    "hint": null,
    "tags": {
        "package": [
            [
                "Condition"
            ]
        ],
        "author": [
            [
                "Guillaume",
                "MOREL",
                "<gmorel@openstudio.fr>"
            ]
        ]
    },
    "namespace": "Thelia\\Condition\\Implementation",
    "file": "\/home\/manu\/dev\/www\/thelia\/core\/lib\/Thelia\/Condition\/Implementation\/MatchForXArticlesManager.php",
    "hash": "d45213b0cf00a1477425ce897370cfd5db7db977",
    "parent": "Thelia\\Condition\\ConditionManagerAbstract",
    "modifiers": 0,
    "is_trait": false,
    "is_interface": false,
    "aliases": {
        "InvalidArgumentException": "InvalidArgumentException",
        "ConditionManagerAbstract": "Thelia\\Condition\\ConditionManagerAbstract",
        "Operators": "Thelia\\Condition\\Operators",
        "InvalidConditionOperatorException": "Thelia\\Exception\\InvalidConditionOperatorException",
        "InvalidConditionValueException": "Thelia\\Exception\\InvalidConditionValueException"
    },
    "errors": [

    ],
    "interfaces": [

    ],
    "properties": [

    ],
    "methods": {
        "setValidatorsFromForm": {
            "name": "setValidatorsFromForm",
            "line": 71,
            "short_desc": "Check validators relevancy and store them",
            "long_desc": "",
            "hint": [
                [
                    "Thelia\\Condition\\Implementation\\$this",
                    false
                ]
            ],
            "hint_desc": "",
            "tags": [

            ],
            "modifiers": "1",
            "is_by_ref": "",
            "exceptions": [
                [
                    "\\InvalidArgumentException",
                    ""
                ]
            ],
            "errors": [

            ],
            "parameters": {
                "operators": {
                    "name": "operators",
                    "line": 71,
                    "short_desc": "Operators the Admin set in BackOffice",
                    "long_desc": null,
                    "hint": [
                        [
                            "array",
                            false
                        ]
                    ],
                    "tags": [

                    ],
                    "modifiers": "array",
                    "default": null,
                    "is_by_ref": false
                },
                "values": {
                    "name": "values",
                    "line": 71,
                    "short_desc": "Values the Admin set in BackOffice",
                    "long_desc": null,
                    "hint": [
                        [
                            "array",
                            false
                        ]
                    ],
                    "tags": [

                    ],
                    "modifiers": "array",
                    "default": null,
                    "is_by_ref": false
                }
            }
        },
        "isMatching": {
            "name": "isMatching",
            "line": 124,
            "short_desc": "Test if Customer meets conditions",
            "long_desc": "",
            "hint": [
                [
                    "bool",
                    false
                ]
            ],
            "hint_desc": "",
            "tags": [

            ],
            "modifiers": "1",
            "is_by_ref": "",
            "exceptions": [

            ],
            "errors": [

            ],
            "parameters": [

            ]
        },
        "getName": {
            "name": "getName",
            "line": 144,
            "short_desc": "Get I18n name",
            "long_desc": "",
            "hint": [
                [
                    "string",
                    false
                ]
            ],
            "hint_desc": "",
            "tags": [

            ],
            "modifiers": "1",
            "is_by_ref": "",
            "exceptions": [

            ],
            "errors": [

            ],
            "parameters": [

            ]
        },
        "getToolTip": {
            "name": "getToolTip",
            "line": 158,
            "short_desc": "Get I18n tooltip",
            "long_desc": "",
            "hint": [
                [
                    "string",
                    false
                ]
            ],
            "hint_desc": "",
            "tags": [

            ],
            "modifiers": "1",
            "is_by_ref": "",
            "exceptions": [

            ],
            "errors": [

            ],
            "parameters": [

            ]
        }
    },
    "constants": {
        "INPUT1": {
            "name": "INPUT1",
            "line": 46,
            "short_desc": "Condition 1st parameter : quantity",
            "long_desc": ""
        }
    }
}