{
    "name": "Thelia\\Model\\Tools\\PositionManagementTrait",
    "line": 30,
    "short_desc": "",
    "long_desc": "",
    "hint": null,
    "tags": [

    ],
    "namespace": "Thelia\\Model\\Tools",
    "file": "\/home\/manu\/dev\/www\/thelia\/core\/lib\/Thelia\/Model\/Tools\/PositionManagementTrait.php",
    "hash": "02fad1056fa04260d04f0d075ea1b9558d3f44b1",
    "parent": null,
    "modifiers": null,
    "is_trait": true,
    "is_interface": false,
    "aliases": {
        "PropelQuery": "Propel\\Runtime\\ActiveQuery\\PropelQuery",
        "Criteria": "Propel\\Runtime\\ActiveQuery\\Criteria",
        "Propel": "Propel\\Runtime\\Propel"
    },
    "errors": [

    ],
    "interfaces": [

    ],
    "properties": [

    ],
    "methods": {
        "getNextPosition": {
            "name": "getNextPosition",
            "line": 59,
            "short_desc": "Get the position of the next inserted object",
            "long_desc": "",
            "hint": null,
            "hint_desc": null,
            "tags": [

            ],
            "modifiers": "1",
            "is_by_ref": "",
            "exceptions": [

            ],
            "errors": [

            ],
            "parameters": [

            ]
        },
        "movePositionUp": {
            "name": "movePositionUp",
            "line": 75,
            "short_desc": "Move up a object",
            "long_desc": "",
            "hint": null,
            "hint_desc": null,
            "tags": [

            ],
            "modifiers": "1",
            "is_by_ref": "",
            "exceptions": [

            ],
            "errors": [

            ],
            "parameters": [

            ]
        },
        "movePositionDown": {
            "name": "movePositionDown",
            "line": 82,
            "short_desc": "Move down a object",
            "long_desc": "",
            "hint": null,
            "hint_desc": null,
            "tags": [

            ],
            "modifiers": "1",
            "is_by_ref": "",
            "exceptions": [

            ],
            "errors": [

            ],
            "parameters": [

            ]
        },
        "changeAbsolutePosition": {
            "name": "changeAbsolutePosition",
            "line": 151,
            "short_desc": "Changes object position",
            "long_desc": "",
            "hint": null,
            "hint_desc": null,
            "tags": [

            ],
            "modifiers": "1",
            "is_by_ref": "",
            "exceptions": [

            ],
            "errors": [

            ],
            "parameters": {
                "newPosition": {
                    "name": "newPosition",
                    "line": 151,
                    "short_desc": "",
                    "long_desc": null,
                    "hint": [
                        [
                            "Thelia\\Model\\Tools\\newPosition",
                            false
                        ]
                    ],
                    "tags": [

                    ],
                    "modifiers": "",
                    "default": null,
                    "is_by_ref": false
                }
            }
        }
    },
    "constants": [

    ]
}