{
    "name": "Thelia\\Controller\\Admin\\MailingSystemController",
    "line": 22,
    "short_desc": "",
    "long_desc": "",
    "hint": null,
    "tags": [

    ],
    "namespace": "Thelia\\Controller\\Admin",
    "file": "\/home\/manu\/dev\/www\/thelia\/core\/lib\/Thelia\/Controller\/Admin\/MailingSystemController.php",
    "hash": "5391a394d962e5995b0ce93795fc74b6b8143651",
    "parent": "Thelia\\Controller\\Admin\\BaseAdminController",
    "modifiers": 0,
    "is_trait": false,
    "is_interface": false,
    "aliases": {
        "MailingSystemEvent": "Thelia\\Core\\Event\\MailingSystem\\MailingSystemEvent",
        "TheliaEvents": "Thelia\\Core\\Event\\TheliaEvents",
        "AccessManager": "Thelia\\Core\\Security\\AccessManager",
        "FormValidationException": "Thelia\\Form\\Exception\\FormValidationException",
        "MailingSystemModificationForm": "Thelia\\Form\\MailingSystemModificationForm",
        "ConfigQuery": "Thelia\\Model\\ConfigQuery"
    },
    "errors": [

    ],
    "interfaces": [

    ],
    "properties": [

    ],
    "methods": {
        "defaultAction": {
            "name": "defaultAction",
            "line": 26,
            "short_desc": "",
            "long_desc": "",
            "hint": null,
            "hint_desc": null,
            "tags": [

            ],
            "modifiers": "1",
            "is_by_ref": "",
            "exceptions": [

            ],
            "errors": [

            ],
            "parameters": [

            ]
        },
        "updateAction": {
            "name": "updateAction",
            "line": 53,
            "short_desc": "",
            "long_desc": "",
            "hint": null,
            "hint_desc": null,
            "tags": [

            ],
            "modifiers": "1",
            "is_by_ref": "",
            "exceptions": [

            ],
            "errors": [

            ],
            "parameters": [

            ]
        }
    },
    "constants": {
        "RESOURCE_CODE": {
            "name": "RESOURCE_CODE",
            "line": 24,
            "short_desc": "",
            "long_desc": ""
        }
    }
}